{
"section": "II",
"title": "Calculus to Optimization & Analysis",
"indexUrl": "Mathematics/Calculus/calculus.html",
"baseUrl": "Mathematics/Calculus/",
"parts": [
    {"id": "calc-1",
    "title": "Linear Approximations",
    "url": "linear_approximation.html",
    "keywords": ["Linear approximation", "Linearization", "Differentials", "Product rule", "Gradient", "Quadratic form", "L₂ norm",
                "Euclidean norm", "Tangent line", "Linear operator"]
    },
    {"id": "calc-2",
    "title": "Jacobian",
    "url": "jacobian.html",
    "keywords": ["Jacobian matrix", "Chain rule", "Backpropagation", "Reverse mode automatic differentiation", "Forward mode automatic differentiation",
                "Vector-Jacobian product", "Neural networks", "Loss function"]
    },
    {"id": "calc-3",
    "title": "Matrix Calculus",
    "url": "matrix_cal.html",
    "keywords": ["Matrix calculus", "Powers of a matrix", "Inverse of a matrix", "LU decomposition", "Matrix-valued functions", "Product rule for matrices",
                "Non-commutative operations"]
    },
    {"id": "calc-4",
    "title": "Intro to Numerical Computation",
    "url": "numerical_example1.html",
    "keywords": ["Finite-difference approximation", "Forward difference", "Backward difference", "Relative error", "Roundoff error",
                "Machine epsilon", "Numerical stability", "Floating-point arithmetic"]
    },
    { "id": "calc-5",
    "title": "Scalar Functions of a Matrix",
    "url": "det.html",
    "keywords": ["Frobenius inner product", "Frobenius norm", "Trace", "Determinant", "Cofactor", "Adjugate", "Characteristic polynomial",
                "Automatic differentiation"]
    },
    {"id": "calc-6",
    "title": "The Mean Value Theorem",
    "url": "mvt.html",
    "keywords": ["Rolle's Theorem", "Lagrange's Mean Value Theorem", "Cauchy's Mean Value Theorem", "Taylor's Theorem", "Taylor polynomial",
                "Taylor series", "Lagrange remainder", "little-o notation", "Higher-dimensional MVT", "Linearization"]
    },
    {"id": "calc-7",
    "title": "Gradient Descent (First-order Method)",
    "url": "gradient.html",
    "keywords": ["Optimization problems", "Convexity", "Convex functions", "Gradient Descent (GD)", "Steepest Descent", "Stochastic Gradient Descent (SGD)",
                "Mini-batch SGD", "Sub-gradient", "Sub-differentiable", "Learning rate", "Local minimum", "Global minimum"]
    },
    {"id": "calc-8",
    "title": "Newton's method (Second-order Method)",
    "url": "newton.html",
    "keywords": ["Line search", "Armijo condition", "Curvature condition", "Wolfe conditions", "Newton's method", "Quasi-Newton methods", "BFGS",
                "L-BFGS", "Secant condition", "Inverse Hessian approximation", "Rosenbrock function", "Second-order optimization"]
    },
    {"id": "calc-9",
    "title": "Constrained Optimization",
    "url": "constrained_opt.html",
    "keywords": ["Constrained optimization problems", "Penalty terms", "Lagrange Multipliers", "Lagrangian", "Karush-Kuhn-Tucker (KKT) conditions",
                "Active set", "Slack variables", "Complementary slackness", "Primal feasibility", "Dual feasibility"]
    },
    {"id": "calc-10",
    "title": "Riemann Integration",
    "url": "riemann.html",
    "keywords": ["Riemann integral", "Riemann integrable", "Improper Riemann integration", "Partition", "Upper sum", "Lower sum", "Dirichlet function",
                "Dense sets", "Gaussian integral", "Cauchy distribution"]
    },
    {"id": "calc-11",
    "title": "Measure Theory with Probability",
    "url": "measure.html",
    "keywords": ["Sample space", "σ-algebra", "σ-field", "Measurable set", "Measurable space", "Measure", "Probability measure", "Probability space",
                "Countable additivity", "Borel σ-algebra", "Borel set", "Lebesgue measure", "Caratheodory Extension Theorem"]
    },
    { "id": "calc-12",
    "title": "Intro to Lebesgue Integration",
    "url": "lebesgue.html",
    "keywords": ["Lebesgue integral", "Abstract integration", "Characteristic function", "Indicator function", "Simple function", "Almost everywhere (a.e.)",
                "Almost surely (a.s.)", "Measurable function", "Dirichlet function", "Dirichlet integral", "Sinc function"]
    },
    {"id": "calc-13",
    "title": "Duality in Optimization & Analysis",
    "url": "duality.html",
    "keywords": ["Duality", "Primal problem", "Dual problem", "Weak duality", "Strong duality", "Duality gap", "Slater's condition", "Smoothness",
                "L-smooth", "Lipschitz continuity", "Contraction mapping", "Convergence rate", "Condition number"]
    },
    {"id": "calc-14",
    "title": "Fourier Series",
    "url": "fourier_series.html",
    "keywords": ["Fourier series", "Fourier coefficients", "Orthogonality of Trigonometric Functions", "Complex exponential form", "Parseval's identity",
                "L² convergence", "Gibbs phenomenon", "Periodic functions", "Harmonic analysis", "Signal decomposition"]
    },
    {"id": "calc-15",
    "title": "Fourier Transform",
    "url": "fourier_transform.html",
    "keywords": ["Fourier transform", "Inverse Fourier transform", "Plancherel's theorem", "Convolution theorem", "Discrete Fourier Transform (DFT)",
                "Fast Fourier Transform (FFT)", "Fourier Neural Operators (FNO)", "Frequency domain", "Signal processing", "Spectral analysis"]
    },
    {"id": "calc-16",
    "title": "Foundations of Analysis: Metric Spaces",
    "url": "metric_space.html",
    "keywords": ["Metric Space", "Distance", "Isolated Points", "Accumulation Points", "Nearest Points", "Boundary", "Interior", "Closure",
                "Open and Closed Sets", "Topology", "Completeness", "Open Balls", "Closed Balls", "Convexity"]
    },
    {"id": "calc-17",
    "title": "Convergence & Boundedness",
    "url": "limit_convergence.html",
    "keywords": ["Tails", "Convergence", "Limits", "Cauchy Sequences", "Boundedness", "Diameter", "Total Boundedness", "Completeness",
                "Sequences", "Metric Spaces", "Gradient Descent Convergence", "Iterative Algorithms"]
    },
    {"id": "calc-18", 
    "title": "Continuity",
    "url": "continuity.html",
    "keywords": ["Continuity", "Uniform Continuity", "Lipschitz Continuity", "Lipschitz Constant", "Contraction", "Strong Contraction",
                "Isometry", "Homeomorphism", "Metric Spaces"]
    },
    {"id": "calc-19",
    "title": "Completeness",
    "url": "completeness.html",
    "keywords": ["Completeness", "Complete Metric Space", "Cauchy Sequence", "Banach's Fixed-Point Theorem", "Contraction Mapping",
                "Completion of Metric Spaces", "Cantor's Intersection Theorem", "Convergence Rate"]
    },
    {"id": "calc-20",
    "title": "Connectedness",
    "url": "connectedness.html",
    "keywords": ["Connectedness", "Path-Connectedness", "Connected Components", "Separation", "Intermediate Value Theorem", "DBSCAN",
                "Spectral Clustering", "Mode Connectivity", "Optimization", "Manifold"]
    },
    {"id": "calc-21",
    "title": "Compactness",
    "url": "compactness.html",
    "keywords": ["Compactness", "Open Cover", "Finite Subcover", "Heine-Borel Theorem", "Extreme Value Theorem", "Sequential Compactness", 
                "Total Boundedness", "Uniform Continuity", "Bolzano-Weierstrass Theorem"]
    },
    {"id": "calc-22",
    "title": "Metric Equivalence",
    "url": "homeomorphism.html",
    "keywords": ["Homeomorphism", "Topological Equivalence", "Uniform Equivalence", "Lipschitz Equivalence", "Topological Invariant",
                "Metric Equivalence", "Bi-continuity"]
    }
]
}